Workbook

Sheet Trade Log
A1: Trade ID | B1: Status | C1: Ticker | D1: Signal Date | E1: Entry Date | F1: Entry Price | G1: Shares | H1: Current Price | I1: Last Price Update | J1: Exit Date | K1: Exit Price | L1: Exit Reason | M1: Target Price | N1: Stop Price | O1: Max Hold Date | P1: Effective Price | Q1: Return % | R1: Days Held | S1: Days Since Price Update | T1: Position Cost | U1: Current/Final Value | V1: P/L $ | W1: Auto Exit Signal | X1: Action | Y1: Notes
A2: =IF(C2="","",ROW()-1) | B2: =IF(AND(J2<>"",K2<>""),"Closed",IF(AND(C2<>"",E2<>"",F2<>""),"Open","")) | L2: =IF(B2<>"Closed","",IF(K2>=M2,"Target",IF(K2<=N2,"Stop",IF(R2>=Settings!$B$4,"Time","Manual")))) | M2: =IF(F2="","",F2*(1+Settings!$B$2)) | N2: =IF(F2="","",F2*(1-Settings!$B$3)) | O2: =IF(E2="","",E2+Settings!$B$4) | P2: =IF(B2="","",IF(B2="Closed",K2,IF(H2="","",H2))) | Q2: =IF(OR(B2="",F2="",P2=""),"",P2/F2-1) | R2: =IF(E2="","",IF(B2="Closed",J2-E2,TODAY()-E2)) | S2: =IF(I2="","",TODAY()-I2) | T2: =IF(OR(F2="",G2=""),"",F2*G2) | U2: =IF(OR(B2="",P2="",G2=""),"",P2*G2) | V2: =IF(OR(B2="",P2="",F2="",G2=""),"",(P2-F2)*G2) | W2: =IF(B2="Closed","CLOSED",IF(B2<>"Open","",IF(H2="","ENTER CURRENT PRICE",IF(H2>=M2,"SELL - TARGET",IF(H2<=N2,"SELL - STOP",IF(TODAY()>=O2,"SELL - TIME","HOLD")))))) | X2: =IF(W2="","",IF(W2="HOLD","Monitor",IF(W2="ENTER CURRENT PRICE","Update price",IF(W2="CLOSED","No action","Review / sell"))))
A3: =IF(C3="","",ROW()-1) | B3: =IF(AND(J3<>"",K3<>""),"Closed",IF(AND(C3<>"",E3<>"",F3<>""),"Open","")) | L3: =IF(B3<>"Closed","",IF(K3>=M3,"Target",IF(K3<=N3,"Stop",IF(R3>=Settings!$B$4,"Time","Manual")))) | M3: =IF(F3="","",F3*(1+Settings!$B$2)) | N3: =IF(F3="","",F3*(1-Settings!$B$3)) | O3: =IF(E3="","",E3+Settings!$B$4) | P3: =IF(B3="","",IF(B3="Closed",K3,IF(H3="","",H3))) | Q3: =IF(OR(B3="",F3="",P3=""),"",P3/F3-1) | R3: =IF(E3="","",IF(B3="Closed",J3-E3,TODAY()-E3)) | S3: =IF(I3="","",TODAY()-I3) | T3: =IF(OR(F3="",G3=""),"",F3*G3) | U3: =IF(OR(B3="",P3="",G3=""),"",P3*G3) | V3: =IF(OR(B3="",P3="",F3="",G3=""),"",(P3-F3)*G3) | W3: =IF(B3="Closed","CLOSED",IF(B3<>"Open","",IF(H3="","ENTER CURRENT PRICE",IF(H3>=M3,"SELL - TARGET",IF(H3<=N3,"SELL - STOP",IF(TODAY()>=O3,"SELL - TIME","HOLD")))))) | X3: =IF(W3="","",IF(W3="HOLD","Monitor",IF(W3="ENTER CURRENT PRICE","Update price",IF(W3="CLOSED","No action","Review / sell"))))
A4: =IF(C4="","",ROW()-1) | B4: =IF(AND(J4<>"",K4<>""),"Closed",IF(AND(C4<>"",E4<>"",F4<>""),"Open","")) | L4: =IF(B4<>"Closed","",IF(K4>=M4,"Target",IF(K4<=N4,"Stop",IF(R4>=Settings!$B$4,"Time","Manual")))) | M4: =IF(F4="","",F4*(1+Settings!$B$2)) | N4: =IF(F4="","",F4*(1-Settings!$B$3)) | O4: =IF(E4="","",E4+Settings!$B$4) | P4: =IF(B4="","",IF(B4="Closed",K4,IF(H4="","",H4))) | Q4: =IF(OR(B4="",F4="",P4=""),"",P4/F4-1) | R4: =IF(E4="","",IF(B4="Closed",J4-E4,TODAY()-E4)) | S4: =IF(I4="","",TODAY()-I4) | T4: =IF(OR(F4="",G4=""),"",F4*G4) | U4: =IF(OR(B4="",P4="",G4=""),"",P4*G4) | V4: =IF(OR(B4="",P4="",F4="",G4=""),"",(P4-F4)*G4) | W4: =IF(B4="Closed","CLOSED",IF(B4<>"Open","",IF(H4="","ENTER CURRENT PRICE",IF(H4>=M4,"SELL - TARGET",IF(H4<=N4,"SELL - STOP",IF(TODAY()>=O4,"SELL - TIME","HOLD")))))) | X4: =IF(W4="","",IF(W4="HOLD","Monitor",IF(W4="ENTER CURRENT PRICE","Update price",IF(W4="CLOSED","No action","Review / sell"))))
A5: =IF(C5="","",ROW()-1) | B5: =IF(AND(J5<>"",K5<>""),"Closed",IF(AND(C5<>"",E5<>"",F5<>""),"Open","")) | L5: =IF(B5<>"Closed","",IF(K5>=M5,"Target",IF(K5<=N5,"Stop",IF(R5>=Settings!$B$4,"Time","Manual")))) | M5: =IF(F5="","",F5*(1+Settings!$B$2)) | N5: =IF(F5="","",F5*(1-Settings!$B$3)) | O5: =IF(E5="","",E5+Settings!$B$4) | P5: =IF(B5="","",IF(B5="Closed",K5,IF(H5="","",H5))) | Q5: =IF(OR(B5="",F5="",P5=""),"",P5/F5-1) | R5: =IF(E5="","",IF(B5="Closed",J5-E5,TODAY()-E5)) | S5: =IF(I5="","",TODAY()-I5) | T5: =IF(OR(F5="",G5=""),"",F5*G5) | U5: =IF(OR(B5="",P5="",G5=""),"",P5*G5) | V5: =IF(OR(B5="",P5="",F5="",G5=""),"",(P5-F5)*G5) | W5: =IF(B5="Closed","CLOSED",IF(B5<>"Open","",IF(H5="","ENTER CURRENT PRICE",IF(H5>=M5,"SELL - TARGET",IF(H5<=N5,"SELL - STOP",IF(TODAY()>=O5,"SELL - TIME","HOLD")))))) | X5: =IF(W5="","",IF(W5="HOLD","Monitor",IF(W5="ENTER CURRENT PRICE","Update price",IF(W5="CLOSED","No action","Review / sell"))))
A6: =IF(C6="","",ROW()-1) | B6: =IF(AND(J6<>"",K6<>""),"Closed",IF(AND(C6<>"",E6<>"",F6<>""),"Open","")) | L6: =IF(B6<>"Closed","",IF(K6>=M6,"Target",IF(K6<=N6,"Stop",IF(R6>=Settings!$B$4,"Time","Manual")))) | M6: =IF(F6="","",F6*(1+Settings!$B$2)) | N6: =IF(F6="","",F6*(1-Settings!$B$3)) | O6: =IF(E6="","",E6+Settings!$B$4) | P6: =IF(B6="","",IF(B6="Closed",K6,IF(H6="","",H6))) | Q6: =IF(OR(B6="",F6="",P6=""),"",P6/F6-1) | R6: =IF(E6="","",IF(B6="Closed",J6-E6,TODAY()-E6)) | S6: =IF(I6="","",TODAY()-I6) | T6: =IF(OR(F6="",G6=""),"",F6*G6) | U6: =IF(OR(B6="",P6="",G6=""),"",P6*G6) | V6: =IF(OR(B6="",P6="",F6="",G6=""),"",(P6-F6)*G6) | W6: =IF(B6="Closed","CLOSED",IF(B6<>"Open","",IF(H6="","ENTER CURRENT PRICE",IF(H6>=M6,"SELL - TARGET",IF(H6<=N6,"SELL - STOP",IF(TODAY()>=O6,"SELL - TIME","HOLD")))))) | X6: =IF(W6="","",IF(W6="HOLD","Monitor",IF(W6="ENTER CURRENT PRICE","Update price",IF(W6="CLOSED","No action","Review / sell"))))
A7: =IF(C7="","",ROW()-1) | B7: =IF(AND(J7<>"",K7<>""),"Closed",IF(AND(C7<>"",E7<>"",F7<>""),"Open","")) | L7: =IF(B7<>"Closed","",IF(K7>=M7,"Target",IF(K7<=N7,"Stop",IF(R7>=Settings!$B$4,"Time","Manual")))) | M7: =IF(F7="","",F7*(1+Settings!$B$2)) | N7: =IF(F7="","",F7*(1-Settings!$B$3)) | O7: =IF(E7="","",E7+Settings!$B$4) | P7: =IF(B7="","",IF(B7="Closed",K7,IF(H7="","",H7))) | Q7: =IF(OR(B7="",F7="",P7=""),"",P7/F7-1) | R7: =IF(E7="","",IF(B7="Closed",J7-E7,TODAY()-E7)) | S7: =IF(I7="","",TODAY()-I7) | T7: =IF(OR(F7="",G7=""),"",F7*G7) | U7: =IF(OR(B7="",P7="",G7=""),"",P7*G7) | V7: =IF(OR(B7="",P7="",F7="",G7=""),"",(P7-F7)*G7) | W7: =IF(B7="Closed","CLOSED",IF(B7<>"Open","",IF(H7="","ENTER CURRENT PRICE",IF(H7>=M7,"SELL - TARGET",IF(H7<=N7,"SELL - STOP",IF(TODAY()>=O7,"SELL - TIME","HOLD")))))) | X7: =IF(W7="","",IF(W7="HOLD","Monitor",IF(W7="ENTER CURRENT PRICE","Update price",IF(W7="CLOSED","No action","Review / sell"))))
A8: =IF(C8="","",ROW()-1) | B8: =IF(AND(J8<>"",K8<>""),"Closed",IF(AND(C8<>"",E8<>"",F8<>""),"Open","")) | L8: =IF(B8<>"Closed","",IF(K8>=M8,"Target",IF(K8<=N8,"Stop",IF(R8>=Settings!$B$4,"Time","Manual")))) | M8: =IF(F8="","",F8*(1+Settings!$B$2)) | N8: =IF(F8="","",F8*(1-Settings!$B$3)) | O8: =IF(E8="","",E8+Settings!$B$4) | P8: =IF(B8="","",IF(B8="Closed",K8,IF(H8="","",H8))) | Q8: =IF(OR(B8="",F8="",P8=""),"",P8/F8-1) | R8: =IF(E8="","",IF(B8="Closed",J8-E8,TODAY()-E8)) | S8: =IF(I8="","",TODAY()-I8) | T8: =IF(OR(F8="",G8=""),"",F8*G8) | U8: =IF(OR(B8="",P8="",G8=""),"",P8*G8) | V8: =IF(OR(B8="",P8="",F8="",G8=""),"",(P8-F8)*G8) | W8: =IF(B8="Closed","CLOSED",IF(B8<>"Open","",IF(H8="","ENTER CURRENT PRICE",IF(H8>=M8,"SELL - TARGET",IF(H8<=N8,"SELL - STOP",IF(TODAY()>=O8,"SELL - TIME","HOLD")))))) | X8: =IF(W8="","",IF(W8="HOLD","Monitor",IF(W8="ENTER CURRENT PRICE","Update price",IF(W8="CLOSED","No action","Review / sell"))))
A9: =IF(C9="","",ROW()-1) | B9: =IF(AND(J9<>"",K9<>""),"Closed",IF(AND(C9<>"",E9<>"",F9<>""),"Open","")) | L9: =IF(B9<>"Closed","",IF(K9>=M9,"Target",IF(K9<=N9,"Stop",IF(R9>=Settings!$B$4,"Time","Manual")))) | M9: =IF(F9="","",F9*(1+Settings!$B$2)) | N9: =IF(F9="","",F9*(1-Settings!$B$3)) | O9: =IF(E9="","",E9+Settings!$B$4) | P9: =IF(B9="","",IF(B9="Closed",K9,IF(H9="","",H9))) | Q9: =IF(OR(B9="",F9="",P9=""),"",P9/F9-1) | R9: =IF(E9="","",IF(B9="Closed",J9-E9,TODAY()-E9)) | S9: =IF(I9="","",TODAY()-I9) | T9: =IF(OR(F9="",G9=""),"",F9*G9) | U9: =IF(OR(B9="",P9="",G9=""),"",P9*G9) | V9: =IF(OR(B9="",P9="",F9="",G9=""),"",(P9-F9)*G9) | W9: =IF(B9="Closed","CLOSED",IF(B9<>"Open","",IF(H9="","ENTER CURRENT PRICE",IF(H9>=M9,"SELL - TARGET",IF(H9<=N9,"SELL - STOP",IF(TODAY()>=O9,"SELL - TIME","HOLD")))))) | X9: =IF(W9="","",IF(W9="HOLD","Monitor",IF(W9="ENTER CURRENT PRICE","Update price",IF(W9="CLOSED","No action","Review / sell"))))
A10: =IF(C10="","",ROW()-1) | B10: =IF(AND(J10<>"",K10<>""),"Closed",IF(AND(C10<>"",E10<>"",F10<>""),"Open","")) | L10: =IF(B10<>"Closed","",IF(K10>=M10,"Target",IF(K10<=N10,"Stop",IF(R10>=Settings!$B$4,"Time","Manual")))) | M10: =IF(F10="","",F10*(1+Settings!$B$2)) | N10: =IF(F10="","",F10*(1-Settings!$B$3)) | O10: =IF(E10="","",E10+Settings!$B$4) | P10: =IF(B10="","",IF(B10="Closed",K10,IF(H10="","",H10))) | Q10: =IF(OR(B10="",F10="",P10=""),"",P10/F10-1) | R10: =IF(E10="","",IF(B10="Closed",J10-E10,TODAY()-E10)) | S10: =IF(I10="","",TODAY()-I10) | T10: =IF(OR(F10="",G10=""),"",F10*G10) | U10: =IF(OR(B10="",P10="",G10=""),"",P10*G10) | V10: =IF(OR(B10="",P10="",F10="",G10=""),"",(P10-F10)*G10) | W10: =IF(B10="Closed","CLOSED",IF(B10<>"Open","",IF(H10="","ENTER CURRENT PRICE",IF(H10>=M10,"SELL - TARGET",IF(H10<=N10,"SELL - STOP",IF(TODAY()>=O10,"SELL - TIME","HOLD")))))) | X10: =IF(W10="","",IF(W10="HOLD","Monitor",IF(W10="ENTER CURRENT PRICE","Update price",IF(W10="CLOSED","No action","Review / sell"))))
A11: =IF(C11="","",ROW()-1) | B11: =IF(AND(J11<>"",K11<>""),"Closed",IF(AND(C11<>"",E11<>"",F11<>""),"Open","")) | L11: =IF(B11<>"Closed","",IF(K11>=M11,"Target",IF(K11<=N11,"Stop",IF(R11>=Settings!$B$4,"Time","Manual")))) | M11: =IF(F11="","",F11*(1+Settings!$B$2)) | N11: =IF(F11="","",F11*(1-Settings!$B$3)) | O11: =IF(E11="","",E11+Settings!$B$4) | P11: =IF(B11="","",IF(B11="Closed",K11,IF(H11="","",H11))) | Q11: =IF(OR(B11="",F11="",P11=""),"",P11/F11-1) | R11: =IF(E11="","",IF(B11="Closed",J11-E11,TODAY()-E11)) | S11: =IF(I11="","",TODAY()-I11) | T11: =IF(OR(F11="",G11=""),"",F11*G11) | U11: =IF(OR(B11="",P11="",G11=""),"",P11*G11) | V11: =IF(OR(B11="",P11="",F11="",G11=""),"",(P11-F11)*G11) | W11: =IF(B11="Closed","CLOSED",IF(B11<>"Open","",IF(H11="","ENTER CURRENT PRICE",IF(H11>=M11,"SELL - TARGET",IF(H11<=N11,"SELL - STOP",IF(TODAY()>=O11,"SELL - TIME","HOLD")))))) | X11: =IF(W11="","",IF(W11="HOLD","Monitor",IF(W11="ENTER CURRENT PRICE","Update price",IF(W11="CLOSED","No action","Review / sell"))))
A12: =IF(C12="","",ROW()-1) | B12: =IF(AND(J12<>"",K12<>""),"Closed",IF(AND(C12<>"",E12<>"",F12<>""),"Open","")) | L12: =IF(B12<>"Closed","",IF(K12>=M12,"Target",IF(K12<=N12,"Stop",IF(R12>=Settings!$B$4,"Time","Manual")))) | M12: =IF(F12="","",F12*(1+Settings!$B$2)) | N12: =IF(F12="","",F12*(1-Settings!$B$3)) | O12: =IF(E12="","",E12+Settings!$B$4) | P12: =IF(B12="","",IF(B12="Closed",K12,IF(H12="","",H12))) | Q12: =IF(OR(B12="",F12="",P12=""),"",P12/F12-1) | R12: =IF(E12="","",IF(B12="Closed",J12-E12,TODAY()-E12)) | S12: =IF(I12="","",TODAY()-I12) | T12: =IF(OR(F12="",G12=""),"",F12*G12) | U12: =IF(OR(B12="",P12="",G12=""),"",P12*G12) | V12: =IF(OR(B12="",P12="",F12="",G12=""),"",(P12-F12)*G12) | W12: =IF(B12="Closed","CLOSED",IF(B12<>"Open","",IF(H12="","ENTER CURRENT PRICE",IF(H12>=M12,"SELL - TARGET",IF(H12<=N12,"SELL - STOP",IF(TODAY()>=O12,"SELL - TIME","HOLD")))))) | X12: =IF(W12="","",IF(W12="HOLD","Monitor",IF(W12="ENTER CURRENT PRICE","Update price",IF(W12="CLOSED","No action","Review / sell"))))
A13: =IF(C13="","",ROW()-1) | B13: =IF(AND(J13<>"",K13<>""),"Closed",IF(AND(C13<>"",E13<>"",F13<>""),"Open","")) | L13: =IF(B13<>"Closed","",IF(K13>=M13,"Target",IF(K13<=N13,"Stop",IF(R13>=Settings!$B$4,"Time","Manual")))) | M13: =IF(F13="","",F13*(1+Settings!$B$2)) | N13: =IF(F13="","",F13*(1-Settings!$B$3)) | O13: =IF(E13="","",E13+Settings!$B$4) | P13: =IF(B13="","",IF(B13="Closed",K13,IF(H13="","",H13))) | Q13: =IF(OR(B13="",F13="",P13=""),"",P13/F13-1) | R13: =IF(E13="","",IF(B13="Closed",J13-E13,TODAY()-E13)) | S13: =IF(I13="","",TODAY()-I13) | T13: =IF(OR(F13="",G13=""),"",F13*G13) | U13: =IF(OR(B13="",P13="",G13=""),"",P13*G13) | V13: =IF(OR(B13="",P13="",F13="",G13=""),"",(P13-F13)*G13) | W13: =IF(B13="Closed","CLOSED",IF(B13<>"Open","",IF(H13="","ENTER CURRENT PRICE",IF(H13>=M13,"SELL - TARGET",IF(H13<=N13,"SELL - STOP",IF(TODAY()>=O13,"SELL - TIME","HOLD")))))) | X13: =IF(W13="","",IF(W13="HOLD","Monitor",IF(W13="ENTER CURRENT PRICE","Update price",IF(W13="CLOSED","No action","Review / sell"))))
... A301: =IF(C301="","",ROW()-1) | B301: =IF(AND(J301<>"",K301<>""),"Closed",IF(AND(C301<>"",E301<>"",F301<>""),"Open","")) | L301: =IF(B301<>"Closed","",IF(K301>=M301,"Target",IF(K301<=N301,"Stop",IF(R301>=Settings!$B$4,"Time","Manual")))) | M301: =IF(F301="","",F301*(1+Settings!$B$2)) | N301: =IF(F301="","",F301*(1-Settings!$B$3)) | O301: =IF(E301="","",E301+Settings!$B$4) | P301: =IF(B301="","",IF(B301="Closed",K301,IF(H301="","",H301))) | Q301: =IF(OR(B301="",F301="",P301=""),"",P301/F301-1) | R301: =IF(E301="","",IF(B301="Closed",J301-E301,TODAY()-E301)) | S301: =IF(I301="","",TODAY()-I301) | T301: =IF(OR(F301="",G301=""),"",F301*G301) | U301: =IF(OR(B301="",P301="",G301=""),"",P301*G301) | V301: =IF(OR(B301="",P301="",F301="",G301=""),"",(P301-F301)*G301) | W301: =IF(B301="Closed","CLOSED",IF(B301<>"Open","",IF(H301="","ENTER CURRENT PRICE",IF(H301>=M301,"SELL - TARGET",IF(H301<=N301,"SELL - STOP",IF(TODAY()>=O301,"SELL - TIME","HOLD")))))) | X301: =IF(W301="","",IF(W301="HOLD","Monitor",IF(W301="ENTER CURRENT PRICE","Update price",IF(W301="CLOSED","No action","Review / sell"))))

Sheet Dashboard
A1: Trade Tracker Dashboard
A2: Metric | B2: Value | C2: Notes
A3: Open positions | B3: =COUNTIF('Trade Log'!B:B,"Open") -> 0 | C3: Currently active trades
A4: Closed trades | B4: =COUNTIF('Trade Log'!B:B,"Closed") -> 0 | C4: Completed records
A5: Open sell/review signals | B5: =COUNTIF('Trade Log'!W:W,"SELL*") -> 0 | C5: Rows requiring attention
A6: Total realized P/L | B6: =SUMIFS('Trade Log'!V:V,'Trade Log'!B:B,"Closed") -> 0 | C6: Closed trades only
A7: Total unrealized P/L | B7: =SUMIFS('Trade Log'!V:V,'Trade Log'!B:B,"Open") -> 0 | C7: Open trades only
A8: Average realized return | B8: =IFERROR(AVERAGEIFS('Trade Log'!Q:Q,'Trade Log'!B:B,"Closed"),"") | C8: Closed trades only
A9: Win rate | B9: =IFERROR(COUNTIFS('Trade Log'!B:B,"Closed",'Trade Log'!Q:Q,">0")/COUNTIF('Trade Log'!B:B,"Closed"),"") | C9: Closed profitable trades / closed trades
A10: Target exits | B10: =COUNTIFS('Trade Log'!B:B,"Closed",'Trade Log'!L:L,"Target") -> 0 | C10: Closed by target
A11: Stop exits | B11: =COUNTIFS('Trade Log'!B:B,"Closed",'Trade Log'!L:L,"Stop") -> 0 | C11: Closed by stop
A12: Time exits | B12: =COUNTIFS('Trade Log'!B:B,"Closed",'Trade Log'!L:L,"Time") -> 0 | C12: Closed by time rule
A13: Average days held | B13: =IFERROR(AVERAGEIFS('Trade Log'!R:R,'Trade Log'!B:B,"Closed"),"") | C13: Closed trades only
A14: Capital currently deployed | B14: =SUMIFS('Trade Log'!T:T,'Trade Log'!B:B,"Open") -> 0 | C14: Based on entry cost
A15: Max open positions setting | B15: =Settings!B5 -> 10 | C15: Risk control
A16: Portfolio value setting | B16: =Settings!B7 -> 0 | C16: Optional input

Sheet Settings
A1: Setting | B1: Value | C1: Notes
A2: Target profit % | B2: 0.05 | C2: Sell target; default +5%
A3: Stop loss % | B3: 0.05 | C3: Default -5%; change if your tested rule differs
A4: Max holding days | B4: 20 | C4: Calendar-day version for simple manual tracking
A5: Max open positions | B5: 10 | C5: Pilot risk control
A6: Position size % of portfolio | B6: 0.005 | C6: Pilot default: 0.5% per trade
A7: Portfolio value | C7: Optional: enter your portfolio value

Sheet Instructions
A1: Simple Manual Trade Tracker
A2: Use the yellow columns in Trade Log for manual entries: Ticker, Signal Date, Entry Date, Entry Price, Shares, Current Price, Last Price Update, Exit Date, Exit Price, and Notes.
A3: The workbook does not store model internals, model agreement, SPY values, or algorithm details.
A4: For an open trade, enter Current Price and Last Price Update whenever you check the trade.
A5: When you sell, enter Exit Date and Exit Price. The row will automatically become Closed and freeze return/P&L using Exit Price.
A6: Auto Exit Signal uses the Settings sheet: target profit, stop loss, and max holding days.
A7: Default rule: review/sell at +5% target, -5% stop, or after 20 calendar days. Change Settings to adjust.
A8: Dashboard summarizes open trades, closed trades, P/L, win rate, and current sell/review signals.
